network_functions/__init__.py
network_functions/classifiers.py
network_functions/functions.py
network_functions/utils/__init__.py
network_functions/utils/helpers.py
network_functions-0.2.2.dist-info/licenses/LICENSE
network_functions-0.2.2.dist-info/METADATA
network_functions-0.2.2.dist-info/WHEEL
network_functions-0.2.2.dist-info/top_level.txt
network_functions-0.2.2.dist-info/RECORD
